{
  // — Selecciones nacionales —
  "alemania": "Germany",
  "argentina": "Argentina",
  "brasil": "Brazil",
  "francia": "France",
  "españa": "Spain",
  "inglaterra": "England",
  "italia": "Italy",
  "portugal": "Portugal",
  "belgica": "Belgium",
  "paises bajos": "Netherlands",
  "croacia": "Croatia",
  "suiza": "Switzerland",
  "rusia": "Russia",
  "turquia": "Turkey",
  "polonia": "Poland",
  "república checa": "Czech Republic",
  "ucrania": "Ukraine",
  "dinamarca": "Denmark",
  "escocia": "Scotland",
  "irlanda": "Ireland",
  "irlanda del norte": "Northern Ireland",
  "noruega": "Norway",
  "suecia": "Sweden",
  "austria": "Austria",
  "hungría": "Hungary",
  "serbia": "Serbia",
  "rumania": "Romania",
  "bielorrusia": "Belarus",
  "bosnia y herzegovina": "Bosnia and Herzegovina",
  "eslovaquia": "Slovakia",
  "eslovenia": "Slovenia",
  "armenia": "Armenia",
  "azerbaiyán": "Azerbaijan",
  "kazajistán": "Kazakhstan",
  "grecia": "Greece",
  "finlandia": "Finland",
  "letonia": "Latvia",
  "lituania": "Lithuania",
  "luxemburgo": "Luxembourg",
  "malta": "Malta",
  "moldavia": "Moldova",
  "macedonia del norte": "North Macedonia",
  "kosovo": "Kosovo",
  "andorra": "Andorra",
  "san marino": "San Marino",
  "chipre": "Cyprus",
  // AFC (Asia)
  "china": "China PR",
  "japón": "Japan",
  "corea del sur": "South Korea",
  "iran": "Iran",
  "australia": "Australia",
  "arabia saudita": "Saudi Arabia",
  "qatar": "Qatar",
  "emiratos arabes unidos": "UAE",
  "omán": "Oman",
  "irak": "Iraq",
  "tailandia": "Thailand",
  "malasia": "Malaysia",
  "vietnam": "Vietnam",
  "singapur": "Singapore",
  // CAF (África)
  "argelia": "Algeria",
  "senegal": "Senegal",
  "marruecos": "Morocco",
  "nigeria": "Nigeria",
  "costa de marfil": "Ivory Coast",
  "tunez": "Tunisia",
  "ghana": "Ghana",
  "egipto": "Egypt",
  "camerun": "Cameroon",
  "uganda": "Uganda",
  // Concacaf
  "méxico": "Mexico",
  "estados unidos": "USA",
  "canada": "Canada",
  "costarica": "Costa Rica",
  "panama": "Panama",
  "jamaica": "Jamaica",
  // CONMEBOL
  "uruguay": "Uruguay",
  "chile": "Chile",
  "colombia": "Colombia",
  "paraguay": "Paraguay",
  "ecuador": "Ecuador",
  "bolivia": "Bolivia",
  "perú": "Peru",
  "venezuela": "Venezuela",
  // OFC (Oceanía)
  "nueva zelanda": "New Zealand",
  "islas salomon": "Solomon Islands",
  "fiji": "Fiji",
  "tonga": "Tonga",
  // — Clubes destacados (opcional, según ligas) —
  "real madrid": "Real Madrid",
  "barcelona": "Barcelona",
  "manchester united": "Manchester United",
  "manchester city": "Manchester City",
  "chelsea": "Chelsea",
  "arsenal": "Arsenal",
  "liverpool": "Liverpool",
  "bayern munich": "Bayern Munich",
  "borussia dortmund": "Borussia Dortmund",
  "juventus": "Juventus",
  "ac milan": "AC Milan",
  "inter milan": "Inter Milan",
  "psg": "Paris Saint-Germain",
  "ajax": "Ajax",
  "porto": "Porto",
  "benfica": "Benfica",
  "flamengo": "Flamengo",
  "palmeiras": "Palmeiras",
  "boca juniors": "Boca Juniors",
  "river plate": "River Plate",
  "tigres uanl": "Tigres UANL",
  "chivas guadalajara": "Chivas Guadalajara",
  "la galaxy": "LA Galaxy",
  "new york red bulls": "New York Red Bulls",
  "seattle sounders": "Seattle Sounders FC"
}
